[
  {
    "title": "PlayUs",
    "sub": "Family Matching App",
    "url": "https://www.figma.com/design/m5DTiZT4VKN6cFQAzM4EY8/Family-Matching-App?node-id=0-1&t=5zlp1p94HoVG2yfj-1",
    "cover": "/image/Pcover.png",
    "coverAlt": "Play us is the Family Matching Application",
    "thumbnail": "/image/Pthumbnail.png",
    "thumbnailAlt": "Play Us helps you connect with nearby families."
  },
  {
    "title": "Health Mate",
    "sub": "Health Tracker App",
    "url": "https://www.figma.com/design/KDo5XCGJ3VkVFTmh6dCiwq/Health-Tracker-App?node-id=8-907&t=4exNpwetSstlB6l1-1",
    "cover": "/image/Hcover.png",
    "coverAlt": "Health Mate is the Health Track Application",
    "thumbnail": "/image/Hthumbnail.png",
    "thumbnailAlt": "Health Mate helps you design healthy daily habits."
  }
]
